pg_az_cert.py
pg_az_cert-0.1.0.dist-info/WHEEL
pg_az_cert-0.1.0.dist-info/METADATA
pg_az_cert-0.1.0.dist-info/RECORD
